{
  "metadata_ata": {
    "ata_id": "9def9620947c3dcb84029206b35f7201e2b351b4d4e1c9ed464b796069ce593a",
    "titulo_sessao": "ATA DA 172 REUNIÃO ORDINÁRIA, DO 1º ANO, DA 19º LEGISLATURA, REALIZADA EM 27 DE MAIO DE 2025, COM INÍCIO ÀS 14:00 HORAS.",
    "data_sessao": "2025-05-27",
    "numero_sessao": 172,
    "tipo_sessao": "Ordinária"
  },
  "votacoes": [
    {
      "objeto_da_votacao": "Aprovação da ata da Reunião Ordinária realizada em 20 de maio de 2025",
      "resumo": "Aprovação da ata da reunião anterior.",
      "resultado": "Aprovada nos termos do artigo 123 do Regimento Interno",
      "votos": []
    },
    {
      "objeto_da_votacao": "Emenda Modificativa e Supressiva nº 01 ao Projeto de Lei nº 16/2025",
      "resumo": "Emenda ao Projeto de Lei nº 16/2025, alterando o artigo 2º e suprimindo seu parágrafo único.",
      "resultado": "Aprovada por unanimidade de votos, com a ausência do vereador Edival Pereira Rosa.",
      "votos": [
        {
          "vereador": "Clayton Aparecido dos Santos",
          "voto": "Sim"
        },
        {
          "vereador": "Almir de Melo Santos",
          "voto": "Sim"
        },
        {
          "vereador": "Antônio Moreira Sobrinho",
          "voto": "Sim"
        },
        {
          "vereador": "Arildo Guadagnini",
          "voto": "Sim"
        },
        {
          "vereador": "Edemilson Pereira dos Santos",
          "voto": "Sim"
        },
        {
          "vereador": "Edival Pereira Rosa",
          "voto": "Ausente"
        },
        {
          "vereador": "Graziela Costa Leite",
          "voto": "Sim"
        },
        {
          "vereador": "Henrique Balseiros Chamosa Neto",
          "voto": "Sim"
        },
        {
          "vereador": "Luzia de Fátima Izidório Vidal",
          "voto": "Sim"
        },
        {
          "vereador": "Michel Oliveira Rodrigues da Silva",
          "voto": "Sim"
        },
        {
          "vereador": "Rogério dos Santos Filho",
          "voto": "Sim"
        }
      ]
    },
    {
      "objeto_da_votacao": "Projeto de Lei nº 16/2025",
      "resumo": "Determinação de leitos separados para mães de natimorto e óbito fetal em unidades de saúde.",
      "resultado": "Aprovado, com emenda, por unanimidade de votos, com a ausência do vereador Edival Pereira Rosa.",
      "votos": [
        {
          "vereador": "Clayton Aparecido dos Santos",
          "voto": "Sim"
        },
        {
          "vereador": "Almir de Melo Santos",
          "voto": "Sim"
        },
        {
          "vereador": "Antônio Moreira Sobrinho",
          "voto": "Sim"
        },
        {
          "vereador": "Arildo Guadagnini",
          "voto": "Sim"
        },
        {
          "vereador": "Edemilson Pereira dos Santos",
          "voto": "Sim"
        },
        {
          "vereador": "Edival Pereira Rosa",
          "voto": "Ausente"
        },
        {
          "vereador": "Graziela Costa Leite",
          "voto": "Sim"
        },
        {
          "vereador": "Henrique Balseiros Chamosa Neto",
          "voto": "Sim"
        },
        {
          "vereador": "Luzia de Fátima Izidório Vidal",
          "voto": "Sim"
        },
        {
          "vereador": "Michel Oliveira Rodrigues da Silva",
          "voto": "Sim"
        },
        {
          "vereador": "Rogério dos Santos Filho",
          "voto": "Sim"
        }
      ]
    },
    {
      "objeto_da_votacao": "Pedido para encaminhar o projeto de lei nº 16/2025 para expedição do autógrafo, dispensando a redação final",
      "resumo": "Pedido de celeridade no processo de aprovação do projeto de lei nº 16/2025.",
      "resultado": "Aprovado por unanimidade de votos, com a ausência do vereador Edival Pereira Rosa.",
      "votos": [
        {
          "vereador": "Clayton Aparecido dos Santos",
          "voto": "Sim"
        },
        {
          "vereador": "Almir de Melo Santos",
          "voto": "Sim"
        },
        {
          "vereador": "Antônio Moreira Sobrinho",
          "voto": "Sim"
        },
        {
          "vereador": "Arildo Guadagnini",
          "voto": "Sim"
        },
        {
          "vereador": "Edemilson Pereira dos Santos",
          "voto": "Sim"
        },
        {
          "vereador": "Edival Pereira Rosa",
          "voto": "Ausente"
        },
        {
          "vereador": "Graziela Costa Leite",
          "voto": "Sim"
        },
        {
          "vereador": "Henrique Balseiros Chamosa Neto",
          "voto": "Sim"
        },
        {
          "vereador": "Luzia de Fátima Izidório Vidal",
          "voto": "Sim"
        },
        {
          "vereador": "Michel Oliveira Rodrigues da Silva",
          "voto": "Sim"
        },
        {
          "vereador": "Rogério dos Santos Filho",
          "voto": "Sim"
        }
      ]
    },
    {
      "objeto_da_votacao": "Emenda Modificativa nº 01 ao Projeto de Lei nº 20/2025",
      "resumo": "Emenda ao Projeto de Lei nº 20/2025, modificando os artigos 1º, 2º e 3º.",
      "resultado": "Aprovada por unanimidade de votos.",
      "votos": [
        {
          "vereador": "Clayton Aparecido dos Santos",
          "voto": "Sim"
        },
        {
          "vereador": "Almir de Melo Santos",
          "voto": "Sim"
        },
        {
          "vereador": "Antônio Moreira Sobrinho",
          "voto": "Sim"
        },
        {
          "vereador": "Arildo Guadagnini",
          "voto": "Sim"
        },
        {
          "vereador": "Edemilson Pereira dos Santos",
          "voto": "Sim"
        },
        {
          "vereador": "Edival Pereira Rosa",
          "voto": "Sim"
        },
        {
          "vereador": "Graziela Costa Leite",
          "voto": "Sim"
        },
        {
          "vereador": "Henrique Balseiros Chamosa Neto",
          "voto": "Sim"
        },
        {
          "vereador": "Luzia de Fátima Izidório Vidal",
          "voto": "Sim"
        },
        {
          "vereador": "Michel Oliveira Rodrigues da Silva",
          "voto": "Sim"
        },
        {
          "vereador": "Rogério dos Santos Filho",
          "voto": "Sim"
        }
      ]
    },
    {
      "objeto_da_votacao": "Projeto de Lei nº 20/2025",
      "resumo": "Estabelecimento de diretrizes sobre contêineres de lixo e limpeza pública.",
      "resultado": "Aprovado, com emenda, por unanimidade de votos.",
      "votos": [
        {
          "vereador": "Clayton Aparecido dos Santos",
          "voto": "Sim"
        },
        {
          "vereador": "Almir de Melo Santos",
          "voto": "Sim"
        },
        {
          "vereador": "Antônio Moreira Sobrinho",
          "voto": "Sim"
        },
        {
          "vereador": "Arildo Guadagnini",
          "voto": "Sim"
        },
        {
          "vereador": "Edemilson Pereira dos Santos",
          "voto": "Sim"
        },
        {
          "vereador": "Edival Pereira Rosa",
          "voto": "Sim"
        },
        {
          "vereador": "Graziela Costa Leite",
          "voto": "Sim"
        },
        {
          "vereador": "Henrique Balseiros Chamosa Neto",
          "voto": "Sim"
        },
        {
          "vereador": "Luzia de Fátima Izidório Vidal",
          "voto": "Sim"
        },
        {
          "vereador": "Michel Oliveira Rodrigues da Silva",
          "voto": "Sim"
        },
        {
          "vereador": "Rogério dos Santos Filho",
          "voto": "Sim"
        }
      ]
    },
    {
      "objeto_da_votacao": "Pedido para encaminhar o projeto de lei nº 20/2025 para expedição do autógrafo, dispensando a redação final",
      "resumo": "Pedido de celeridade no processo de aprovação do projeto de lei nº 20/2025.",
      "resultado": "Aprovado por unanimidade de votos.",
      "votos": [
        {
          "vereador": "Clayton Aparecido dos Santos",
          "voto": "Sim"
        },
        {
          "vereador": "Almir de Melo Santos",
          "voto": "Sim"
        },
        {
          "vereador": "Antônio Moreira Sobrinho",
          "voto": "Sim"
        },
        {
          "vereador": "Arildo Guadagnini",
          "voto": "Sim"
        },
        {
          "vereador": "Edemilson Pereira dos Santos",
          "voto": "Sim"
        },
        {
          "vereador": "Edival Pereira Rosa",
          "voto": "Sim"
        },
        {
          "vereador": "Graziela Costa Leite",
          "voto": "Sim"
        },
        {
          "vereador": "Henrique Balseiros Chamosa Neto",
          "voto": "Sim"
        },
        {
          "vereador": "Luzia de Fátima Izidório Vidal",
          "voto": "Sim"
        },
        {
          "vereador": "Michel Oliveira Rodrigues da Silva",
          "voto": "Sim"
        },
        {
          "vereador": "Rogério dos Santos Filho",
          "voto": "Sim"
        }
      ]
    }
  ]
}